blend_x_glb/__init__.py
blend_x_glb/blender_export.py
blend_x_glb-1.0.0.dist-info/WHEEL
blend_x_glb-1.0.0.dist-info/entry_points.txt
blend_x_glb-1.0.0.dist-info/METADATA
blend_x_glb-1.0.0.dist-info/RECORD
