Metadata-Version: 2.3
Name: blend-x-glb
Version: 1.0.0
Summary: Add your description here
Requires-Dist: beaupy>=3.11.0
Requires-Dist: typer>=0.21.1
Requires-Python: >=3.13
